rl_agents/__init__.py
rl_agents/agents/__init__.py
rl_agents/agents/core.py
rl_agents/agents/functions/__init__.py
rl_agents/agents/functions/base.py
rl_agents/agents/functions/tabular_functions.py
rl_agents/agents/mab/__init__.py
rl_agents/agents/mab/base.py
rl_agents/agents/mab/egreedy.py
rl_agents/agents/mab/pursuit.py
rl_agents/agents/mab/softmax.py
rl_agents/agents/mab/ucbs.py
rl_agents/agents/policies/__init__.py
rl_agents/agents/policies/tabular_policies.py
rl_agents/agents/tabular/__init__.py
rl_agents/agents/tabular/td_learning.py
rl_agents/envs/__init__.py
rl_agents/envs/k_armed.py
rl_agents/example.py
rl_agents/runners/__init__.py
rl_agents/runners/mab_runner.py
rl_agents/runners/tab_runner.py
rl_agents-0.1.1.dist-info/LICENSE
rl_agents-0.1.1.dist-info/WHEEL
rl_agents-0.1.1.dist-info/METADATA
rl_agents-0.1.1.dist-info/RECORD
