Metadata-Version: 2.1
Name: rl-agents
Version: 0.1.1
Summary: Implementation of various reinforcement learning methods.
Home-page: https://github.com/mateuspontesm/rl-agents
License: BSD-3-Clause
Keywords: rl-agents
Author: Mateus Mota
Author-email: mateuspontesm@outlook.com
Requires-Python: >=3.6,<4.0
Classifier: Development Status :: 2 - Pre-Alpha
Classifier: Intended Audience :: Developers
Classifier: License :: OSI Approved :: BSD License
Classifier: Natural Language :: English
Classifier: Programming Language :: Python
Classifier: Programming Language :: Python :: 3
Classifier: Programming Language :: Python :: 3.6
Classifier: Programming Language :: Python :: 3.7
Classifier: Programming Language :: Python :: 3.8
Classifier: Programming Language :: Python :: Implementation :: CPython
Classifier: Programming Language :: Python :: Implementation :: PyPy
Classifier: Topic :: Software Development
Requires-Dist: gym (>=0.17.2,<0.18.0)
Requires-Dist: numpy (>=1.18.4,<2.0.0)
Requires-Dist: tqdm (>=4.46.0,<5.0.0)
Project-URL: Bug Tracker, https://github.com/mateuspontesm/rl-agents/issues
Project-URL: Documentation, https://rl-agents.readthedocs.io
Project-URL: Repository, https://github.com/mateuspontesm/rl-agents
Project-URL: Source, https://github.com/mateuspontesm/rl-agents
